nicoinfo/plugins/nicoinfo/__init__.py
nicoinfo/plugins/nicoinfo/BB_susume.py
nicoinfo/plugins/nicoinfo/config.py
nicoinfo/plugins/nicoinfo/get_info.py
nicoinfo/plugins/nicoinfo/nico_auth.py
nicoinfo/plugins/nicoinfo/others.py
nicoinfo/plugins/nicoinfo/random_cookie_image.py
nicoinfo/plugins/nicoinfo/test.py
nicoinfo/plugins/nicoinfo/usage.py
nicoinfo/plugins/nicoinfo/utils.py
nicoinfo/plugins/nicoinfo/wraps.py
nicoinfo-1.0.1.dist-info/METADATA
nicoinfo-1.0.1.dist-info/WHEEL
nicoinfo-1.0.1.dist-info/RECORD
