Metadata-Version: 2.1
Name: nicoinfo
Version: 1.0.1
Summary: n站饼图推送
License: MIT
Author: ECUsam
Author-email: 1254281150@qq.com
Requires-Python: >=3.8,<4.0
Classifier: License :: OSI Approved :: MIT License
Classifier: Programming Language :: Python :: 3
Classifier: Programming Language :: Python :: 3.8
Classifier: Programming Language :: Python :: 3.9
Classifier: Programming Language :: Python :: 3.10
Classifier: Programming Language :: Python :: 3.11
Requires-Dist: PyYAML (==6.0)
Requires-Dist: aiohttp (==3.8.4)
Requires-Dist: aiosignal (==1.3.1)
Requires-Dist: anyio (==3.6.2)
Requires-Dist: async-timeout (==4.0.2)
Requires-Dist: attrs (==23.1.0)
Requires-Dist: beautifulsoup4 (==4.12.2)
Requires-Dist: certifi (==2023.5.7)
Requires-Dist: charset-normalizer (==3.1.0)
Requires-Dist: click (==8.1.3)
Requires-Dist: colorama (==0.4.6)
Requires-Dist: decorator (==5.1.1)
Requires-Dist: fastapi (==0.95.1)
Requires-Dist: frozenlist (==1.3.3)
Requires-Dist: h11 (==0.14.0)
Requires-Dist: httptools (==0.5.0)
Requires-Dist: idna (==3.4)
Requires-Dist: loguru (==0.6.0)
Requires-Dist: lxml (==4.9.2)
Requires-Dist: msgpack (==1.0.5)
Requires-Dist: multidict (==6.0.4)
Requires-Dist: nonebot-adapter-onebot (==2.2.3)
Requires-Dist: nonebot2 (==2.0.0rc4)
Requires-Dist: py (==1.11.0)
Requires-Dist: pydantic (==1.10.7)
Requires-Dist: pygtrie (==2.5.0)
Requires-Dist: python-dotenv (==1.0.0)
Requires-Dist: requests (==2.30.0)
Requires-Dist: retry (==0.9.2)
Requires-Dist: sniffio (==1.3.0)
Requires-Dist: soupsieve (==2.4.1)
Requires-Dist: starlette (==0.26.1)
Requires-Dist: tomli (==2.0.1)
Requires-Dist: typing-extensions (==4.5.0)
Requires-Dist: urllib3 (==2.0.2)
Requires-Dist: uvicorn (==0.22.0)
Requires-Dist: watchfiles (==0.19.0)
Requires-Dist: websockets (==11.0.3)
Requires-Dist: win32-setctime (==1.1.0)
Requires-Dist: yarl (==1.9.2)
